fastapi_tortoise_crud-1.1.1.dist-info/METADATA
fastapi_tortoise_crud-1.1.1.dist-info/WHEEL
fastapi_tortoise_crud-1.1.1.dist-info/entry_points.txt
fastapi_tortoise_crud/__init__.py
fastapi_tortoise_crud/compatibility/__init__.py
fastapi_tortoise_crud/compatibility/legacy.py
fastapi_tortoise_crud/core/__init__.py
fastapi_tortoise_crud/core/base.py
fastapi_tortoise_crud/core/dependencies.py
fastapi_tortoise_crud/core/models.py
fastapi_tortoise_crud/core/schemas.py
fastapi_tortoise_crud/core/status_codes.py
fastapi_tortoise_crud/core/types.py
fastapi_tortoise_crud/features/__init__.py
fastapi_tortoise_crud/features/caching/__init__.py
fastapi_tortoise_crud/features/caching/backends.py
fastapi_tortoise_crud/features/caching/config.py
fastapi_tortoise_crud/features/caching/global_config.py
fastapi_tortoise_crud/features/caching/manager.py
fastapi_tortoise_crud/features/hooks/__init__.py
fastapi_tortoise_crud/features/hooks/class_based.py
fastapi_tortoise_crud/features/hooks/config.py
fastapi_tortoise_crud/features/hooks/manager.py
fastapi_tortoise_crud/features/hooks/registry.py
fastapi_tortoise_crud/features/hooks/response_handler.py
fastapi_tortoise_crud/features/hooks/types.py
fastapi_tortoise_crud/features/monitoring/__init__.py
fastapi_tortoise_crud/features/monitoring/config.py
fastapi_tortoise_crud/features/monitoring/manager.py
fastapi_tortoise_crud/features/monitoring/metrics.py
fastapi_tortoise_crud/features/monitoring/middleware.py
fastapi_tortoise_crud/features/relations/__init__.py
fastapi_tortoise_crud/features/relations/handlers.py
fastapi_tortoise_crud/features/relations/utils.py
fastapi_tortoise_crud/routes/__init__.py
fastapi_tortoise_crud/routes/crud.py
fastapi_tortoise_crud/routes/factory.py
fastapi_tortoise_crud/utils/__init__.py
fastapi_tortoise_crud/utils/exceptions.py
fastapi_tortoise_crud/utils/helpers.py
fastapi_tortoise_crud/utils/schema_generator.py
fastapi_tortoise_crud-1.1.1.dist-info/RECORD
