Metadata-Version: 2.1
Name: fastapi-tortoise-crud
Version: 1.1.1
Summary: A powerful FastAPI + Tortoise ORM CRUD library with advanced features: auto-relation queries, time-range filters, fine-grained dependency injection, unified response format, and intelligent caching
Keywords: FastAPI,Tortoise-ORM,CRUD,Cache,Hooks,REST-API,Auto-Relations,Time-Filters,Dependency-Injection,Schema-Generation
Author-Email: moxiaoying <768091671@qq.com>
License: MIT
Requires-Python: >=3.11
Requires-Dist: tortoise-orm>=0.20.0
Requires-Dist: fastapi>=0.115.12
Requires-Dist: pydantic>=2.0.0
Requires-Dist: typing-extensions>=4.0.0
Provides-Extra: redis
Requires-Dist: redis>=4.0.0; extra == "redis"
